dj_chartjs/__init__.py
dj_chartjs/admin.py
dj_chartjs/apps.py
dj_chartjs/charts.py
dj_chartjs/models.py
dj_chartjs/tests.py
dj_chartjs/urls.py
dj_chartjs/views.py
dj_chartjs/migrations/__init__.py
dj_chartjs/static/css/Chart.min.css
dj_chartjs/static/css/django_charts.css
dj_chartjs/static/img/.gitignore
dj_chartjs/static/js/Chart.bundle.min.js
dj_chartjs/static/js/django-charts.js
dj_chartjs/templates/dj_chartjs/base.html
dj_chartjs/templates/dj_chartjs/chart.html
dj_chartjs/templatetags/__init__.py
dj_chartjs/templatetags/dj_chartjs.py
dj_chartjs/test_utils/__init__.py
dj_chartjs/test_utils/test_app/__init__.py
dj_chartjs/test_utils/test_app/admin.py
dj_chartjs/test_utils/test_app/apps.py
dj_chartjs/test_utils/test_app/models.py
dj_chartjs/test_utils/test_app/migrations/__init__.py
dj_chartjs/tests/__init__.py
dj_chartjs/tests/test_context_chart.py
tests/__init__.py
tests/settings.py
tests/test_context_chart.py
tests/test_models.py
tests/urls.py
dj_chartjs-1.0.7.dist-info/AUTHORS.rst
dj_chartjs-1.0.7.dist-info/LICENSE
dj_chartjs-1.0.7.dist-info/METADATA
dj_chartjs-1.0.7.dist-info/WHEEL
dj_chartjs-1.0.7.dist-info/top_level.txt
dj_chartjs-1.0.7.dist-info/RECORD
