Metadata-Version: 2.1
Name: dj-chartjs
Version: 1.0.7
Summary: Library to render chart using chartjs
Home-page: https://github.com/ramon5/django-charts
Author: Ramon dos Santos Rodrigues
Author-email: ramon.srodrigues01@gmail.com
License: MIT
Keywords: dj-chartjs
Platform: UNKNOWN
Classifier: Development Status :: 3 - Alpha
Classifier: Framework :: Django :: 1.11
Classifier: Framework :: Django :: 3.0
Classifier: Intended Audience :: Developers
Classifier: License :: OSI Approved :: BSD License
Classifier: Natural Language :: English
Classifier: Programming Language :: Python :: 2
Classifier: Programming Language :: Python :: 2.7
Classifier: Programming Language :: Python :: 3
Classifier: Programming Language :: Python :: 3.5
Classifier: Programming Language :: Python :: 3.6
Requires-Python: >=3.6
